btparser/__init__.py
btparser/btparser.py
btparser-0.1.0.dist-info/DESCRIPTION.rst
btparser-0.1.0.dist-info/METADATA
btparser-0.1.0.dist-info/metadata.json
btparser-0.1.0.dist-info/RECORD
btparser-0.1.0.dist-info/top_level.txt
btparser-0.1.0.dist-info/WHEEL
