Metadata-Version: 2.0
Name: btparser
Version: 0.1.0
Summary: A Bittorent file parser written as a part of the interview process of Light Speed Retail
Home-page: https://github.com/amertkara/btparser
Author: A. Mert Kara
Author-email: amertkara@gmail.com
License: BSD
Keywords: btparser
Platform: UNKNOWN
Classifier: Development Status :: 2 - Pre-Alpha
Classifier: Intended Audience :: Developers
Classifier: License :: OSI Approved :: BSD License
Classifier: Natural Language :: English
Classifier: Programming Language :: Python :: 2
Classifier: Programming Language :: Python :: 2.6
Classifier: Programming Language :: Python :: 2.7
Classifier: Programming Language :: Python :: 3
Classifier: Programming Language :: Python :: 3.3
Classifier: Programming Language :: Python :: 3.4
